hafnian/__init__.py
hafnian/_hafnian.py
hafnian/_permanent.py
hafnian/_torontonian.py
hafnian/_version.py
hafnian/quantum.py
hafnian/reference.py
hafnian/samples.py
hafnian/.libs/libkinds.Y5UQ6PGFSBTRL23XIIO6OR3L7ONE5BAN.gfortran-win_amd64.dll
hafnian/lib/libhaf.cp35-win_amd64.pyd
hafnian/lib/libperm.cp35-win_amd64.pyd
hafnian/tests/conftest.py
hafnian/tests/test_hafnian.py
hafnian/tests/test_hafnian_approx.py
hafnian/tests/test_hafnian_repeated.py
hafnian/tests/test_permanent.py
hafnian/tests/test_quantum.py
hafnian/tests/test_reference.py
hafnian/tests/test_samples.py
hafnian/tests/test_torontonian.py
hafnian-0.6.1.dist-info/LICENSE
hafnian-0.6.1.dist-info/METADATA
hafnian-0.6.1.dist-info/WHEEL
hafnian-0.6.1.dist-info/top_level.txt
hafnian-0.6.1.dist-info/RECORD
